{
  "window.zoomLevel": -1,
  "workbench.sideBar.location": "right",
  "workbench.colorTheme": "One Dark Pro Darker",
  "workbench.iconTheme": "material-icon-theme",
  "workbench.editor.wrapTabs": true,
  "editor.formatOnSave": true,
  "editor.fontLigatures": true,
  "editor.tabSize": 2,
  "editor.fontSize": 15,
  "editor.fontFamily": "Fira Code",
  "terminal.integrated.fontFamily": "Menlo, Monaco, 'Courier New', monospace",
  "terminal.integrated.fontSize": 15,
  "[typescriptreact]": {
    "editor.defaultFormatter": "esbenp.prettier-vscode"
  },
  "[postcss]": {
    "editor.defaultFormatter": "stylelint.vscode-stylelint"
  },
  "[javascript]": {
    "editor.defaultFormatter": "esbenp.prettier-vscode"
  },
  "[typescript]": {
    "editor.defaultFormatter": "esbenp.prettier-vscode"
  },
  "[json]": {
    "editor.defaultFormatter": "esbenp.prettier-vscode"
  }
}
